<?xml version="1.0" encoding="UTF-8"?>
<!-- edited with XMLSPY v2004 rel. 4 U (http://www.xmlspy.com) by Gon (ORiON) -->
<systemtree systemid="KA0VD0" mmcid="" version="" date="" author="" history="">
  <commset moduleid="" testerid="" vsschannel="0x0800" protocolid="0x100017">
    <funcsupport>
      <function index="1000" desc="1" />
      <function index="3000" desc="3" />
      <function index="5000" desc="5" />
    </funcsupport>
    <hardwareset commrelay="0x2000" k_lineselect="0x0000" k_linestatus="0x0010" l_lineselect="0x0002" l_linestatus="0x0020" k_lineswitchstatus="0x0004" l_lineswitchstatus="0x0008" rxlineselect="0x0068" rxlinestatus="0x0000" pulluprelay="0x0000" k_linepullup="0x0001" l_linepullup="0x0002" l_linegnd="0x0000" k_linech="0x0010" l_linech="0x0100" rprogramch="0x0000" etc1="" etc2="" etc3="" etc4="" etc5="1" />
    <j2534setconfig datarate="9600" loopback="0" nodeaddress="0x00" networkline="0" p1min="0x0000" p1max="0x0014" p2min="0x0019" p2max="0x0032" p3min="0x03E8" p3max="0x1388" p4min="0x0005" p4max="0x0014" w1="0x03E8" w2="0x03E8" w3="0x03E8" w4="0x001E" w5="0x012C" tidle="0x0BB8" tinil="0x0019" twup="0x0032" parity="0" bitsamplepoint="80" syncjumpwidth="15" t1max="0x0014" t2max="0x0064" t3max="0x0032" t4max="0x0014" t5max="0x0064" iso15765bs="0x00" iso15765stmin="0x00" bstx="0xFFFF" stmintx="0xFFFF" databits="0" fivebaudmod="0" toolmanufacturerspec="0" etc1="" etc2="" etc3="" etc4="" etc5="" />
    <initaddress>
      <initaddressvalue address="10" />
      <initaddressvalue address="" />
    </initaddress>
    <startcomm>
      <requestnode request="11" response="51XX46XX53XX5F" />
    </startcomm>
    <commchannel>
      <kline>
        <klinechannel channel="0x0010" />
      </kline>
    </commchannel>
    <acknowledge request="" response="" />
    <commdown>
      <requestnode request="20" response="" />
    </commdown>
  </commset>
  <dtc functionid="1000" functionname="자기진단" functiontype="7" requesttime="1" searchtype="1" startpos="2" readno="1" skipno="0" totalmasking="FF">
    <requestcodetree>
      <requestnode index="1" request="11" response="51XX46XX53XX5F" />
      <requestnode index="" request="" response="" />
      <requestnode index="" request="" response="" />
    </requestcodetree>
    <dtcitemtree header="25" index="25-12" maskingvalue="FF" commcode="0101" compid="">
      <freezeindex index="" />
    </dtcitemtree>
    <dtcitemtree header="26" index="P1170" maskingvalue="FF" commcode="0102" compid="">
      <freezeindex index="" />
    </dtcitemtree>
    <dtcitemtree header="14" index="14-10" maskingvalue="FF" commcode="0104" compid="">
      <freezeindex index="" />
    </dtcitemtree>
    <dtcitemtree header="86" index="86-1" maskingvalue="FF" commcode="0108" compid="">
      <freezeindex index="" />
    </dtcitemtree>
    <dtcitemtree header="09" index="09-1" maskingvalue="FF" commcode="0110" compid="">
      <freezeindex index="" />
    </dtcitemtree>
    <dtcitemtree header="23" index="P1127-2" maskingvalue="FF" commcode="0120" compid="">
      <freezeindex index="" />
    </dtcitemtree>
    <dtcitemtree header="12" index="12-1" maskingvalue="FF" commcode="0140" compid="">
      <freezeindex index="" />
    </dtcitemtree>
    <dtcitemtree header="01" index="01" maskingvalue="FF" commcode="0180" compid="">
      <freezeindex index="" />
    </dtcitemtree>
    <dtcitemtree header="02" index="02-6" maskingvalue="FF" commcode="0301" compid="">
      <freezeindex index="" />
    </dtcitemtree>
    <dtcitemtree header="96" index="96" maskingvalue="FF" commcode="0302" compid="">
      <freezeindex index="" />
    </dtcitemtree>
    <dtcitemtree header="06" index="P0500" maskingvalue="FF" commcode="0304" compid="">
      <freezeindex index="" />
    </dtcitemtree>
    <dtcitemtree header="31" index="31-11" maskingvalue="FF" commcode="0308" compid="">
      <freezeindex index="" />
    </dtcitemtree>
    <dtcitemtree header="98" index="98" maskingvalue="FF" commcode="0310" compid="">
      <freezeindex index="" />
    </dtcitemtree>
    <dtcitemtree header="34" index="10" maskingvalue="FF" commcode="0320" compid="">
      <freezeindex index="" />
    </dtcitemtree>
    <dtcitemtree header="33" index="33-6" maskingvalue="FF" commcode="0340" compid="">
      <freezeindex index="" />
    </dtcitemtree>
    <dtcitemtree header="32" index="32-8" maskingvalue="FF" commcode="0380" compid="">
      <freezeindex index="" />
    </dtcitemtree>
    <dtcitemtree header="50" index="C030" maskingvalue="FF" commcode="0501" compid="">
      <freezeindex index="" />
    </dtcitemtree>
    <dtcitemtree header="49" index="49-3" maskingvalue="FF" commcode="0502" compid="">
      <freezeindex index="" />
    </dtcitemtree>
    <dtcitemtree header="46" index="46-5" maskingvalue="FF" commcode="0504" compid="">
      <freezeindex index="" />
    </dtcitemtree>
    <dtcitemtree header="45" index="45-6" maskingvalue="FF" commcode="0508" compid="">
      <freezeindex index="" />
    </dtcitemtree>
    <dtcitemtree header="44" index="44-10" maskingvalue="FF" commcode="0510" compid="">
      <freezeindex index="" />
    </dtcitemtree>
    <dtcitemtree header="43" index="43-9" maskingvalue="FF" commcode="0520" compid="">
      <freezeindex index="" />
    </dtcitemtree>
    <dtcitemtree header="42" maskingvalue="FF" commcode="0540" compid="" index="42-3">
      <freezeindex index="" />
    </dtcitemtree>
    <dtcitemtree header="41" index="XX-3" maskingvalue="FF" commcode="0580" compid="">
      <freezeindex index="" />
    </dtcitemtree>
    <dtcitemtree header="94" index="94" maskingvalue="FF" commcode="0701" compid="">
      <freezeindex index="" />
    </dtcitemtree>
    <dtcitemtree header="95" index="95-2" maskingvalue="FF" commcode="0702" compid="">
      <freezeindex index="" />
    </dtcitemtree>
    <dtcitemtree header="97" index="97-2" maskingvalue="FF" commcode="0704" compid="">
      <freezeindex index="" />
    </dtcitemtree>
    <dtcitemtree header="93" index="93-2" maskingvalue="FF" commcode="0708" compid="">
      <freezeindex index="" />
    </dtcitemtree>
    <dtcitemtree header="99" index="99-1" maskingvalue="FF" commcode="0710" compid="">
      <freezeindex index="" />
    </dtcitemtree>
    <dtcitemtree header="48" index="P1325-1" maskingvalue="FF" commcode="0780" compid="">
      <freezeindex index="" />
    </dtcitemtree>
  </dtc>
  <erasememory functionid="2000" functionname="EraseMemory" functiontype="0" startrequiretime="0" endrequiretime="0" requesttime="3">
    <requestnode index="1" request="11" response="XX" />
    <requestnode index="" request="" response="" />
    <requestnode index="" request="" response="" />
    <requestnode index="" request="" response="" />
  </erasememory>
  <currentdata functionid="3000" functionname="Current Data" functiontype="0" requesttime="1">
    <requestnode request="" response="" />
    <requestnode request="" response="" />
    <currentdatanode header="" index="8" requestcode="11" response="C1XXXXC9XXXXD0" startpos="1" realpos="2" datasize="2" datatype="1" minvalue="00" maxvalue="FFFF" unit="5" floatrange="1" compid="14200100" freeze="">
      <convrule convtype="1" A="0.097993" B="0" C="" D="" E="" F="" />
    </currentdatanode>
    <currentdatanode header="" index="54" requestcode="11" response="C1XXXXC9XXXXD0" startpos="1" realpos="5" datasize="2" datatype="1" minvalue="00" maxvalue="FFFF" unit="8" floatrange="2" compid="14200800" freeze="">
      <convrule convtype="1" A="0.001532" B="0" C="" D="" E="" F="" />
    </currentdatanode>
    <currentdatanode header="" index="56" requestcode="11" response="C1XXXXC9XXXXD0" startpos="1" realpos="8" datasize="2" datatype="1" minvalue="00" maxvalue="FFFF" unit="12" floatrange="2" compid="14900500" freeze="">
      <convrule convtype="1" A="0.000977" B="0" C="" D="" E="" F="" />
    </currentdatanode>
    <currentdatanode header="" requestcode="11" response="C1XXXXC9XXXXD0" startpos="1" realpos="11" datasize="2" datatype="1" minvalue="00" maxvalue="FFFF" unit="4" floatrange="2" compid="" freeze="" index="6621">
      <convrule convtype="1" A="0.000077" B="0" C="" D="" E="" F="" />
    </currentdatanode>
    <currentdatanode header="" index="6" requestcode="11" response="C1XXXXC9XXXXD0" startpos="1" realpos="14" datasize="1" datatype="1" minvalue="00" maxvalue="FF" unit="3" floatrange="1" compid="14200600" freeze="">
      <convrule convtype="1" A="0.6667" B="-40" C="" D="" E="" F="" />
    </currentdatanode>
    <currentdatanode header="" index="61" requestcode="11" response="C1XXXXC9XXXXD0" startpos="1" realpos="16" datasize="1" datatype="1" minvalue="00" maxvalue="FF" unit="3" floatrange="1" compid="13300310" freeze="">
      <convrule convtype="1" A="0.6667" B="-40" C="" D="" E="" F="" />
    </currentdatanode>
    <currentdatanode header="" index="59" requestcode="11" response="C1XXXXC9XXXXD0" startpos="1" realpos="21" datasize="1" datatype="1" minvalue="00" maxvalue="FF" unit="8" floatrange="2" compid="" freeze="">
      <convrule convtype="1" A="0.392" B="0" C="" D="" E="" F="" />
    </currentdatanode>
    <currentdatanode header="" index="5947" requestcode="11" response="C1XXXXC9XXXXD0" startpos="1" realpos="23" datasize="2" datatype="1" minvalue="00" maxvalue="FFFF" unit="2" floatrange="1" compid="" freeze="">
      <convrule convtype="1" A="0.01563" B="0" C="" D="" E="" F="" />
    </currentdatanode>
    <currentdatanode header="" index="55" requestcode="11" response="C1XXXXC9XXXXD0" startpos="1" realpos="26" datasize="2" datatype="1" minvalue="00" maxvalue="FFFF" unit="2" floatrange="1" compid="14204300" freeze="">
      <convrule convtype="1" A="0.039063" B="0" C="" D="" E="" F="" />
    </currentdatanode>
    <currentdatanode header="" index="9" requestcode="11" response="C1XXXXC9XXXXD0" startpos="1" realpos="29" datasize="2" datatype="1" minvalue="00" maxvalue="FFFF" unit="6" floatrange="1" compid="14201400" freeze="">
      <convrule convtype="1" A="0.003906" B="0" C="" D="" E="" F="" />
    </currentdatanode>
    <currentdatanode header="" index="3" requestcode="11" response="C1XXXXC9XXXXD0" startpos="1" realpos="37" datasize="1" datatype="1" minvalue="00" maxvalue="FF" unit="3" floatrange="1" compid="14200500" freeze="">
      <convrule convtype="1" A="0.6667" B="-40" C="" D="" E="" F="" />
    </currentdatanode>
    <currentdatanode header="" index="6624" requestcode="11" response="C1XXXXC9XXXXD0" startpos="1" realpos="39" datasize="1" datatype="1" minvalue="00" maxvalue="FF" unit="50" floatrange="1" compid="" freeze="">
      <convrule convtype="20" A="363" B="" C="" D="0xFF" E="" F="" />
    </currentdatanode>
    <currentdatanode header="" index="58" requestcode="11" response="C1XXXXC9XXXXD0" startpos="1" realpos="57" datasize="2" datatype="1" minvalue="00" maxvalue="FFFF" unit="13" floatrange="3" compid="" freeze="">
      <convrule convtype="1" A="0.000214" B="0" C="" D="" E="" F="" />
    </currentdatanode>
    <currentdatanode header="" index="57" requestcode="11" response="C1XXXXC9XXXXD0" startpos="1" realpos="60" datasize="2" datatype="1" minvalue="00" maxvalue="FFFF" unit="13" floatrange="3" compid="" freeze="">
      <convrule convtype="1" A="0.000214" B="0" C="" D="" E="" F="" />
    </currentdatanode>
    <currentdatanode header="" index="167" requestcode="11" response="C1XXXXC9XXXXD0" startpos="1" realpos="84" datasize="2" datatype="1" minvalue="00" maxvalue="FFFF" unit="5" floatrange="1" compid="14202000" freeze="">
      <convrule convtype="1" A="0.097993" B="0" C="" D="" E="" F="" />
    </currentdatanode>
    <currentdatanode header="" index="2070" requestcode="11" response="C1XXXXC9XXXXD0" startpos="1" realpos="41" datasize="1" datatype="1" minvalue="00" maxvalue="FF" unit="" floatrange="1" compid="" freeze="">
      <convrule convtype="3" A="1" B="1" C="1" D="0x80" E="" F="" />
    </currentdatanode>
    <currentdatanode header="" index="2071" requestcode="11" response="C1XXXXC9XXXXD0" startpos="1" realpos="41" datasize="1" datatype="1" minvalue="00" maxvalue="FF" unit="" floatrange="1" compid="14900500" freeze="">
      <convrule convtype="3" A="1" B="1" C="1" D="0x20" E="" F="" />
    </currentdatanode>
    <currentdatanode header="" index="2072" requestcode="11" response="C1XXXXC9XXXXD0" startpos="1" realpos="41" datasize="1" datatype="1" minvalue="00" maxvalue="FF" unit="" floatrange="1" compid="14202000" freeze="">
      <convrule convtype="3" A="1" B="1" C="1" D="0x08" E="" F="" />
    </currentdatanode>
    <currentdatanode header="" index="2073" requestcode="11" response="C1XXXXC9XXXXD0" startpos="1" realpos="41" datasize="1" datatype="1" minvalue="00" maxvalue="FF" unit="" floatrange="1" compid="" freeze="">
      <convrule convtype="3" A="1" B="1" C="1" D="0x02" E="" F="" />
    </currentdatanode>
    <currentdatanode header="" index="2074" requestcode="11" response="C1XXXXC9XXXXD0" startpos="1" realpos="41" datasize="1" datatype="1" minvalue="00" maxvalue="FF" unit="" floatrange="1" compid="14200800" freeze="">
      <convrule convtype="3" A="1" B="1" C="1" D="0x01" E="" F="" />
    </currentdatanode>
  </currentdata>
  <ecuinfo functionid="5000" functionname="1" functiontype="0">
    <ecuinfonode index="10" startpos="51" readno="2" maskingvalue="FFFF" expresstype="2">
      <requestnode request="11" response="C1XXXXC9XXXXD0" />
    </ecuinfonode>
    <ecuinfonode index="84" startpos="54" readno="2" maskingvalue="FFFF" expresstype="2">
      <requestnode request="11" response="C1XXXXC9XXXXD0" />
    </ecuinfonode>
    <ecuinfonode index="14" startpos="93" readno="1" maskingvalue="FF" expresstype="104">
      <requestnode request="11" response="C1XXXXC9XXXXD0" />
    </ecuinfonode>
  </ecuinfo>
</systemtree>